setup.py
elections/__init__.py
elections/ap.py
python_elections.egg-info/PKG-INFO
python_elections.egg-info/SOURCES.txt
python_elections.egg-info/dependency_links.txt
python_elections.egg-info/requires.txt
python_elections.egg-info/top_level.txt