Metadata-Version: 1.1
Name: python-elections
Version: 1.1.1
Summary: A Python wrapper for the AP's U.S. election data service.
Home-page: http://www.github.com/datadesk/python-elections/
Author: The Los Angeles Times Data Desk
Author-email: datadesk@latimes.com
License: UNKNOWN
Platform: UNKNOWN
Classifier: Programming Language :: Python
Classifier: Programming Language :: Python :: 2.6
Classifier: Programming Language :: Python :: 2.7
